{
  "requests": [
    20,
    30,
    20,
    40
  ],
  "enrollments": [
    {
      "decay_time": 20,
      "pointers": [
        15030468,
        2741486,
        15081796,
        13098468,
        14662504,
        3659057,
        15378470,
        10828002,
        14191043,
        1300268,
        11456109,
        10031070,
        13061237,
        3281905,
        12095483,
        11927729,
        10117607,
        13307059,
        10076935,
        8827694,
        1213783,
        1656563,
        7030387,
        13196180,
        11261268,
        15831090,
        4069097,
        1846157,
        6281177,
        8449871,
        5837811,
        10711723
      ],
      "auth_value": 3295163474,
      "parity": [
        26,
        41,
        32,
        111,
        118,
        195,
        30,
        229,
        96
      ]
    },
    {
      "decay_time": 30,
      "pointers": [
        4553528,
        1490426,
        16353294,
        3407353,
        10253107,
        9978485,
        4739739,
        14015561,
        6260990,
        8891041,
        14340321,
        11798913,
        5599586,
        12271752,
        7418939,
        5054955,
        3513312,
        88126,
        497642,
        6606212,
        11521962,
        12539596,
        7868780,
        6841350,
        15524960,
        663440,
        1804534,
        8134696,
        3591396,
        14689631,
        16415624,
        10684540
      ],
      "auth_value": 2501297922,
      "parity": [
        194,
        94,
        4,
        174,
        75,
        36,
        255,
        28,
        184
      ]
    },
    {
      "decay_time": 40,
      "pointers": [
        2257643,
        16491006,
        6948709,
        8293751,
        4452077,
        8575717,
        5638639,
        1483620,
        12079339,
        16063094,
        3627642,
        15582717,
        10849268,
        11822370,
        16175837,
        13925749,
        5754040,
        4683437,
        2661385,
        12579749,
        350906,
        14767679,
        11779441,
        3693580,
        1435977,
        9590060,
        11962660,
        8777008,
        15242810,
        2889463,
        6492390,
        11005114
      ],
      "auth_value": 2893781533,
      "parity": [
        7,
        247,
        22,
        41,
        112,
        194,
        201,
        63,
        150
      ]
    },
    {
      "decay_time": 50,
      "pointers": [
        13365094,
        6708282,
        10177481,
        16216752,
        5644443,
        5936878,
        8677043,
        10199570,
        10008208,
        7200366,
        12509073,
        8543674,
        1713052,
        15248703,
        12427377,
        3736060,
        11403116,
        3443755,
        7334819,
        7090550,
        3891340,
        8788259,
        3532916,
        16604583,
        866554,
        4796005,
        7993447,
        8602893,
        11171509,
        7301600,
        6888891,
        10484467
      ],
      "auth_value": 3621906538,
      "parity": [
        30,
        245,
        145,
        222,
        239,
        222,
        198,
        10,
        51
      ]
    },
    {
      "decay_time": 60,
      "pointers": [
        11176437,
        9744863,
        12433638,
        13185529,
        15340082,
        10152098,
        1644719,
        10574646,
        12808623,
        16137271,
        16622274,
        8674093,
        15589252,
        13551022,
        6993020,
        15328865,
        12816057,
        5504811,
        7784084,
        2262396,
        6313213,
        229229,
        6400034,
        15624507,
        1897207,
        13127088,
        16291371,
        1851855,
        9503280,
        2322204,
        1481598,
        8226477
      ],
      "auth_value": 3623070500,
      "parity": [
        225,
        228,
        57,
        109,
        2,
        123,
        249,
        21,
        224
      ]
    }
  ]
}